vanguards/NodeSelection.py
vanguards/__init__.py
vanguards/bandguards.py
vanguards/cbtverify.py
vanguards/config.py
vanguards/control.py
vanguards/logger.py
vanguards/main.py
vanguards/rendguard.py
vanguards/vanguards.py
vanguards-0.3.1.dist-info/DESCRIPTION.rst
vanguards-0.3.1.dist-info/LICENSE.txt
vanguards-0.3.1.dist-info/METADATA
vanguards-0.3.1.dist-info/RECORD
vanguards-0.3.1.dist-info/WHEEL
vanguards-0.3.1.dist-info/entry_points.txt
vanguards-0.3.1.dist-info/metadata.json
vanguards-0.3.1.dist-info/top_level.txt
