Metadata-Version: 2.0
Name: vanguards
Version: 0.3.1
Summary: Vanguards help guard you from getting vanned...
Home-page: https://github.com/mikeperry-tor/vanguards
Author: Mike Perry
Author-email: UNKNOWN
License: MIT/Expat
Keywords: tor
Platform: UNKNOWN
Classifier: Development Status :: 4 - Beta
Classifier: License :: OSI Approved :: MIT License
Classifier: Programming Language :: Python :: 2
Classifier: Programming Language :: Python :: 2.7
Classifier: Programming Language :: Python :: 3
Classifier: Programming Language :: Python :: 3.5
Requires-Dist: ipaddress (>=1.0.17)
Requires-Dist: setuptools
Requires-Dist: stem (>=1.7.0)
